pydantic_firebase_remoteconfig/__init__.py
pydantic_firebase_remoteconfig/client.py
pydantic_firebase_remoteconfig/models.py
pydantic_firebase_remoteconfig-0.3.0.dist-info/METADATA
pydantic_firebase_remoteconfig-0.3.0.dist-info/WHEEL
pydantic_firebase_remoteconfig-0.3.0.dist-info/top_level.txt
pydantic_firebase_remoteconfig-0.3.0.dist-info/RECORD
