Metadata-Version: 2.4
Name: pydantic-firebase-remoteconfig
Version: 0.3.0
Summary: A simple Firebase Remote Config binding for Pydantic
Author-email: Félix Voituret <fvoituret@opsie.dev>
Project-URL: Documentation, https://github.com/opsie-dev/pydantic-firebase-remoteconfig
Project-URL: Repository, https://github.com/opsie-dev/pydantic-firebase-remoteconfig
Project-URL: Issues, https://github.com/opsie-dev/pydantic-firebase-remoteconfig/issues
Requires-Python: >=3.12
Requires-Dist: google-auth>=2.41.1
Requires-Dist: google-auth-httplib2>=0.2.0
Requires-Dist: httpx>=0.28.1
Requires-Dist: pydantic-settings>=2.11.0
Requires-Dist: pydantic[email]>=2.11.10
Requires-Dist: requests>=2.32.5
